bluerpc_client/__init__.py
bluerpc_client/bleak.py
bluerpc_client/bluerpc.py
bluerpc_client/characteristic.py
bluerpc_client/crypto.py
bluerpc_client/descriptor.py
bluerpc_client/scanner.py
bluerpc_client/service.py
bluerpc_client/utils.py
bluerpc_client/rpc/__init__.py
bluerpc_client/rpc/common_pb2.py
bluerpc_client/rpc/common_pb2_grpc.py
bluerpc_client/rpc/gatt_pb2.py
bluerpc_client/rpc/gatt_pb2_grpc.py
bluerpc_client/rpc/services_pb2.py
bluerpc_client/rpc/services_pb2_grpc.py
bluerpc_client-0.3.4.dist-info/METADATA
bluerpc_client-0.3.4.dist-info/WHEEL
bluerpc_client-0.3.4.dist-info/top_level.txt
bluerpc_client-0.3.4.dist-info/RECORD
