Metadata-Version: 2.1
Name: bluerpc-client
Version: 0.3.4
Summary: Python BlueRPC Client
Home-page: https://github.com/BlueRPC/BlueRPC
Author: drosocode
License: MIT
Project-URL: Documentation, https://bluerpc.github.io/
Project-URL: Source, https://github.com/BlueRPC/BlueRPC/tree/main/client
Classifier: Programming Language :: Python :: 3
Classifier: License :: OSI Approved :: MIT License
Classifier: Operating System :: OS Independent
Requires-Python: >=3.8
Requires-Dist: async-timeout
Requires-Dist: bleak >=0.20
Requires-Dist: cryptography >=41.0
Requires-Dist: grpcio >=1.52
Requires-Dist: protobuf >=4.23
Requires-Dist: zeroconf
